LICENSE.txt
MANIFEST.in
README.rst
setup.py
roborio_webdash.egg-info/PKG-INFO
roborio_webdash.egg-info/SOURCES.txt
roborio_webdash.egg-info/dependency_links.txt
roborio_webdash.egg-info/entry_points.txt
roborio_webdash.egg-info/requires.txt
roborio_webdash.egg-info/top_level.txt
webdash/Webdash_init.sh
webdash/__init__.py
webdash/main.py
webdash/netconsole_controller.py
webdash/networktables_controller.py
webdash/version.py
webdash/__pycache__/__init__.cpython-34.pyc
webdash/__pycache__/main.cpython-34.pyc
webdash/__pycache__/netconsole_controller.cpython-34.pyc
webdash/__pycache__/networktables_controller.cpython-34.pyc
webdash/resources/FIRSTvert_Reversed.gif
webdash/resources/dashboard.css
webdash/resources/favicon.ico
webdash/resources/index.html
webdash/resources/jquery.min.js
webdash/resources/livewindow.js
webdash/resources/netconsole.js
webdash/resources/networktables.js
webdash/resources/ntwidgets.js
webdash/resources/powered_by_robotpy.png
webdash/resources/utilities.js
webdash/resources/bootstrap/bootstrap-select/bootstrap-select.min.css
webdash/resources/bootstrap/bootstrap-select/bootstrap-select.min.js
webdash/resources/bootstrap/css/bootstrap-theme.css
webdash/resources/bootstrap/css/bootstrap-theme.css.map
webdash/resources/bootstrap/css/bootstrap-theme.min.css
webdash/resources/bootstrap/css/bootstrap.css
webdash/resources/bootstrap/css/bootstrap.css.map
webdash/resources/bootstrap/css/bootstrap.min.css
webdash/resources/bootstrap/fonts/glyphicons-halflings-regular.eot
webdash/resources/bootstrap/fonts/glyphicons-halflings-regular.svg
webdash/resources/bootstrap/fonts/glyphicons-halflings-regular.ttf
webdash/resources/bootstrap/fonts/glyphicons-halflings-regular.woff
webdash/resources/bootstrap/js/bootstrap.js
webdash/resources/bootstrap/js/bootstrap.min.js
webdash/resources/bootstrap/js/npm.js