Metadata-Version: 1.1
Name: roborio-webdash
Version: 2015.0.5
Summary: A web-based dashboard with several useful utilities
Home-page: UNKNOWN
Author: Christian Balcom
Author-email: robot.inventor@gmail.com
License: BSD License
Keywords: frc first robotics networktables netconsole livewindow
Platform: UNKNOWN
Classifier: Development Status :: 5 - Production/Stable
Classifier: Operating System :: OS Independent
Classifier: Environment :: Console
Classifier: Programming Language :: Python
Classifier: License :: OSI Approved :: BSD License
